fifeutil/__init__.py
fifeutil/dotdict.py
fifeutil/interval.py
fifeutil/intervalaccumulator.py
fifeutil/intervalmgr.py
fifeutil/sqlite_data_store.py
fifeutil/timer.py
fifeutil/timing.py
fifeutil-1.0.1.dist-info/LICENSE
fifeutil-1.0.1.dist-info/METADATA
fifeutil-1.0.1.dist-info/WHEEL
fifeutil-1.0.1.dist-info/top_level.txt
fifeutil-1.0.1.dist-info/RECORD
