Metadata-Version: 2.1
Name: fifeutil
Version: 1.0.1
Summary: Utility functions
Home-page: https://github.com/jmfife/fifeutil
Author: Mike Fife
Author-email: "J. M. Fife" <jmfife@gmail.com>
Classifier: Programming Language :: Python :: 3
Classifier: License :: OSI Approved :: MIT License
Classifier: Operating System :: OS Independent
Requires-Python: >=3.7
License-File: LICENSE
Requires-Dist: pandas
